plasmacli/__init__.py
plasmacli/cli.py
plasmacli/component_manager.py
plasmacli/project_manager.py
plasmacli/utils.py
plasmacli/workflow_manager.py
plasma_cli-0.1.4.dist-info/METADATA
plasma_cli-0.1.4.dist-info/WHEEL
plasma_cli-0.1.4.dist-info/entry_points.txt
plasma_cli-0.1.4.dist-info/top_level.txt
plasma_cli-0.1.4.dist-info/RECORD
