Metadata-Version: 2.1
Name: plasma-cli
Version: 0.1.4
Summary: CLI for Plasma, a simple ML workflow management tool. Visit docs.s20.ai to read the docs.
Home-page: https://github.com/tabishimran/plasma-cli
Author: Tabish Imran
Author-email: vector@s20.ai
License: BSD
Platform: any
Classifier: Development Status :: 4 - Beta
Classifier: Environment :: Console
Classifier: Intended Audience :: Developers
Classifier: License :: OSI Approved :: BSD License
Classifier: Operating System :: POSIX
Classifier: Operating System :: MacOS
Classifier: Operating System :: Unix
Classifier: Operating System :: Microsoft :: Windows
Classifier: Programming Language :: Python
Classifier: Programming Language :: Python :: 2
Classifier: Programming Language :: Python :: 3
Classifier: Topic :: Software Development :: Libraries :: Python Modules
Requires-Python: >=3
Requires-Dist: PyYAML
Requires-Dist: click
Requires-Dist: requests
Requires-Dist: xxhash
